xsskiller
